sanic_openapi3e/__init__.py
sanic_openapi3e/doc.py
sanic_openapi3e/oas_types.py
sanic_openapi3e/openapi.py
sanic_openapi3e/swagger.py
sanic_openapi3e/ui/favicon-16x16.png
sanic_openapi3e/ui/favicon-32x32.png
sanic_openapi3e/ui/index.html
sanic_openapi3e/ui/oauth2-redirect.html
sanic_openapi3e/ui/swagger-ui-bundle.js
sanic_openapi3e/ui/swagger-ui-bundle.js.map
sanic_openapi3e/ui/swagger-ui-standalone-preset.js
sanic_openapi3e/ui/swagger-ui-standalone-preset.js.map
sanic_openapi3e/ui/swagger-ui.css
sanic_openapi3e/ui/swagger-ui.css.map
sanic_openapi3e/ui/swagger-ui.js
sanic_openapi3e/ui/swagger-ui.js.map
sanic_openapi3e-0.9.10.dist-info/LICENSE
sanic_openapi3e-0.9.10.dist-info/METADATA
sanic_openapi3e-0.9.10.dist-info/WHEEL
sanic_openapi3e-0.9.10.dist-info/top_level.txt
sanic_openapi3e-0.9.10.dist-info/RECORD
