Metadata-Version: 2.1
Name: sanic-openapi3e
Version: 0.9.10
Summary: OpenAPI v3 support for Sanic. Document and describe all parameters, including sanic path params. Python 3.6+
Home-page: https://github.com/endafarrell/sanic-openapi3e
Author: Enda Farrell
Author-email: enda.farrell@gmail.com
License: MIT
Platform: any
Classifier: Development Status :: 5 - Production/Stable
Classifier: Environment :: Web Environment
Classifier: Intended Audience :: Developers
Classifier: License :: OSI Approved :: MIT License
Classifier: Natural Language :: English
Classifier: Operating System :: OS Independent
Classifier: Programming Language :: Python :: 3 :: Only
Classifier: Programming Language :: Python :: 3.6
Classifier: Programming Language :: Python :: 3.7
Classifier: Programming Language :: Python :: 3.8
Classifier: Programming Language :: Python :: 3.9
Classifier: Programming Language :: Python
Classifier: Topic :: Software Development :: Libraries :: Python Modules
Requires-Dist: sanic (>=19.6.0)
Requires-Dist: pyyaml (>=5.3.1)
Provides-Extra: testing
Requires-Dist: pytest ; extra == 'testing'
Requires-Dist: pytest-cov ; extra == 'testing'
